_mssql.so
pymssql.so
pymssql_nikcub-2.2.0.dist-info/DESCRIPTION.rst
pymssql_nikcub-2.2.0.dist-info/METADATA
pymssql_nikcub-2.2.0.dist-info/RECORD
pymssql_nikcub-2.2.0.dist-info/WHEEL
pymssql_nikcub-2.2.0.dist-info/metadata.json
pymssql_nikcub-2.2.0.dist-info/top_level.txt
